.editorconfig
.gitignore
.gitlab-ci.yml
README.rst
publish.settings.sh
publish.sh
pyproject.toml
tsconfig.json
.idea/modules.xml
.idea/peek-core-api.iml
.idea/inspectionProfiles/Project_Default.xml
.idea/inspectionProfiles/profiles_settings.xml
mock_external_restful_service/docker-compose.yml
peek_core_api/PlatformDependencyTest.py
peek_core_api/__init__.py
peek_core_api/plugin_package.json
peek_core_api.egg-info/PKG-INFO
peek_core_api.egg-info/SOURCES.txt
peek_core_api.egg-info/dependency_links.txt
peek_core_api.egg-info/requires.txt
peek_core_api.egg-info/top_level.txt
peek_core_api/_private/PluginNames.py
peek_core_api/_private/__init__.py
peek_core_api/_private/alembic.ini
peek_core_api/_private/agent/AgentEntryHook.py
peek_core_api/_private/agent/AgentTupleDataObserver.py
peek_core_api/_private/agent/RpcForServer.py
peek_core_api/_private/agent/__init__.py
peek_core_api/_private/agent/controller/OutboundMessageController.py
peek_core_api/_private/agent/controller/__init__.py
peek_core_api/_private/alembic/__init__.py
peek_core_api/_private/alembic/env.py
peek_core_api/_private/alembic/script.py.mako
peek_core_api/_private/alembic/versions/b6ab5ef39719_added_lastpublisheddate.py
peek_core_api/_private/alembic/versions/c31aaab9c30e_add_core_api_tables.py
peek_core_api/_private/logic/AgentTupleDataObservable.py
peek_core_api/_private/logic/LogicEntryHook.py
peek_core_api/_private/logic/TupleDataObservable.py
peek_core_api/_private/logic/__init__.py
peek_core_api/_private/logic/agent_handlers/RpcForAgent.py
peek_core_api/_private/logic/agent_handlers/__init__.py
peek_core_api/_private/logic/api/CoreApi.py
peek_core_api/_private/logic/api/__init__.py
peek_core_api/_private/logic/controller/ApiManagementController.py
peek_core_api/_private/logic/controller/ApiPublishingController.py
peek_core_api/_private/logic/controller/HashController.py
peek_core_api/_private/logic/controller/MainController.py
peek_core_api/_private/logic/controller/MessageQueueController.py
peek_core_api/_private/logic/controller/SqlController.py
peek_core_api/_private/logic/controller/__init__.py
