Metadata-Version: 2.4
Name: peek-core-api
Version: 5.0.4
Summary: Peek Core API - Outbound API with guaranteed delivery
Author-email: Synerty <contact@synerty.com>
Project-URL: Homepage, https://github.com/Synerty/peek-core-api
Keywords: Peek,Python,Platform,synerty
Requires-Dist: peek-plugin-base==5.0.4
Requires-Dist: hashids>=1.3.1
